rcr.cpython-37m-darwin.so
rcr_test.cpython-37m-darwin.so
rcr-2.4.7.dist-info/LICENSE
rcr-2.4.7.dist-info/METADATA
rcr-2.4.7.dist-info/WHEEL
rcr-2.4.7.dist-info/top_level.txt
rcr-2.4.7.dist-info/RECORD
