Metadata-Version: 2.1
Name: rcr
Version: 2.4.7
Summary: Advanced, but easy to use outlier rejection.
Home-page: https://github.com/nickk124/RCR
Author: Nick Konz
Author-email: nickkonz3@gmail.com
License: UNKNOWN
Platform: UNKNOWN
Classifier: Programming Language :: Python :: 3
Classifier: License :: Other/Proprietary License
Classifier: Operating System :: OS Independent
